NetworkScanning/__init__.py
NetworkScanning/banner_grabber.py
NetworkScanning/tcp_scanner.py
NetworkScanning/udp_scanner.py
NetworkScanning/utils.py
NetworkScanning/tests/__init__.py
NetworkScanning/tests/test_banner_grabber.py
NetworkScanning/tests/test_tcp_scanner.py
NetworkScanning/tests/test_udp_scanner.py
NetwrokScanning-0.1.dist-info/LICENSE
NetwrokScanning-0.1.dist-info/METADATA
NetwrokScanning-0.1.dist-info/WHEEL
NetwrokScanning-0.1.dist-info/top_level.txt
NetwrokScanning-0.1.dist-info/RECORD
